setup.py
tesla_lib/__init__.py
tesla_lib/cmp.py
tesla_lib.egg-info/PKG-INFO
tesla_lib.egg-info/SOURCES.txt
tesla_lib.egg-info/dependency_links.txt
tesla_lib.egg-info/entry_points.txt
tesla_lib.egg-info/top_level.txt