Metadata-Version: 1.0
Name: tesla-lib
Version: 0.0.3
Summary: tesla dict校验库
Home-page: UNKNOWN
Author: oyj
Author-email: wisecsj@gmail.com
License: UNKNOWN
Platform: UNKNOWN
